snippets/__init__.py
snippets_dxc-0.0.2.dist-info/METADATA
snippets_dxc-0.0.2.dist-info/WHEEL
snippets_dxc-0.0.2.dist-info/top_level.txt
snippets_dxc-0.0.2.dist-info/RECORD
