Metadata-Version: 2.1
Name: snippets-dxc
Version: 0.0.2
Summary: A small example package
Home-page: https://github.com/DXC-Finsa/ds-snippets
Author: Example Author
Author-email: author@example.com
License: UNKNOWN
Platform: UNKNOWN
Classifier: Programming Language :: Python :: 3
Classifier: License :: OSI Approved :: MIT License
Classifier: Operating System :: OS Independent
Requires-Python: >=3.6
Requires-Dist: google-cloud-storage
